candidate/__init__.py
candidate/base.py
candidate/csv_candidate_provider.py
data/__init__.py
data/base.py
data/monitor_persistence.py
exceptions/__init__.py
exceptions/no_matching_handler.py
handlers/__init__.py
handlers/base.py
handlers/e621_handler.py
handlers/furaffinity_handler.py
uploader/__init__.py
uploader/catbox_uploader.py
uploader/raw_uploader.py
uploader/uploader.py
lemmy_post_automation-1.4.0.dist-info/LICENSE.md
lemmy_post_automation-1.4.0.dist-info/METADATA
lemmy_post_automation-1.4.0.dist-info/WHEEL
lemmy_post_automation-1.4.0.dist-info/top_level.txt
lemmy_post_automation-1.4.0.dist-info/RECORD
